encoders-0.0.4.dist-info/RECORD
encoders-0.0.4.dist-info/WHEEL
encoders-0.0.4.dist-info/top_level.txt
encoders-0.0.4.dist-info/METADATA
encoders/__init__.py
encoders/encoder.py
encoders/cyfuncs.cpython-38-darwin.so
encoders/py.typed
